{
  "dollar": "520,91",
  "states": [
    { "name": "Amazonas", "weather": "☁️ 24°C" },
    { "name": "Anzoátegui", "weather": "🌤️ 17°C" },
    { "name": "Apure", "weather": "☁️ 29°C" },
    { "name": "Aragua", "weather": "☁️ 27°C" },
    { "name": "Barinas", "weather": "☁️ 25°C" },
    { "name": "Bolívar", "weather": "☁️ 26°C" },
    { "name": "Carabobo", "weather": "🌤️ 14°C" },
    { "name": "Cojedes", "weather": "☁️ 27°C" },
    { "name": "Delta Amacuro", "weather": "☁️ 23°C" },
    { "name": "Distrito Capital", "weather": "⛅ 23°C" },
    { "name": "Falcón", "weather": "☁️ 26°C" },
    { "name": "Guárico", "weather": "☁️ 27°C" },
    { "name": "Guayana Esequiba", "weather": "☁️ 23°C" },
    { "name": "La Guaira", "weather": "☁️ 23°C" },
    { "name": "Lara", "weather": "⛅ 26°C" },
    { "name": "Mérida", "weather": "🌦️ 23°C" },
    { "name": "Miranda", "weather": "☀️ 31°C" },
    { "name": "Monagas", "weather": "☁️ 20°C" },
    { "name": "Nueva Esparta", "weather": "☁️ 24°C" },
    { "name": "Portuguesa", "weather": "☁️ 25°C" },
    { "name": "Sucre", "weather": "☁️ 25°C" },
    { "name": "Táchira", "weather": "☁️ 26°C" },
    { "name": "Trujillo", "weather": "☁️ 24°C" },
    { "name": "Yaracuy", "weather": "☁️ 24°C" },
    { "name": "Zulia", "weather": "☁️ 22°C" }
  ]
}